broski.py
broski-0.4.0.dist-info/METADATA
broski-0.4.0.dist-info/WHEEL
broski-0.4.0.dist-info/entry_points.txt
broski-0.4.0.dist-info/top_level.txt
broski-0.4.0.dist-info/RECORD
