Metadata-Version: 2.1
Name: broski
Version: 0.4.0
Summary: Add your description here
Requires-Python: >=3.11
Requires-Dist: click>=8.1.8
Requires-Dist: promptic>=4.0.1
Requires-Dist: rich>=13.9.4
